{"dependencies":[{"name":"/Users/miguelangel.duran/Dev/react-slidy/package.json","includedInParent":true,"mtime":1520010299184},{"name":"/Users/miguelangel.duran/Dev/react-slidy/node_modules/babel-runtime/node_modules/core-js/package.json","includedInParent":true,"mtime":1520010094470},{"name":"./_object-sap","loc":{"line":2,"column":8}},{"name":"./_object-gopn-ext","loc":{"line":3,"column":17}}],"generated":{"js":"// 19.1.2.7 Object.getOwnPropertyNames(O)\nrequire('./_object-sap')('getOwnPropertyNames', function () {\n  return require('./_object-gopn-ext').f;\n});\n","map":{"mappings":[{"source":"../node_modules/babel-runtime/node_modules/core-js/library/modules/es6.object.get-own-property-names.js","original":{"line":1,"column":0},"generated":{"line":1,"column":0}},{"source":"../node_modules/babel-runtime/node_modules/core-js/library/modules/es6.object.get-own-property-names.js","original":{"line":2,"column":0},"generated":{"line":2,"column":0}},{"source":"../node_modules/babel-runtime/node_modules/core-js/library/modules/es6.object.get-own-property-names.js","original":{"line":3,"column":0},"generated":{"line":3,"column":0}},{"source":"../node_modules/babel-runtime/node_modules/core-js/library/modules/es6.object.get-own-property-names.js","original":{"line":4,"column":0},"generated":{"line":4,"column":0}},{"source":"../node_modules/babel-runtime/node_modules/core-js/library/modules/es6.object.get-own-property-names.js","original":{"line":5,"column":0},"generated":{"line":5,"column":0}}],"sources":{"../node_modules/babel-runtime/node_modules/core-js/library/modules/es6.object.get-own-property-names.js":"// 19.1.2.7 Object.getOwnPropertyNames(O)\nrequire('./_object-sap')('getOwnPropertyNames', function () {\n  return require('./_object-gopn-ext').f;\n});\n"},"lineCount":5}},"hash":"3a0ccec080d557b75fe55e2a8a46ab99","cacheData":{"env":{}}}