{"dependencies":[{"name":"/Users/miguelangel.duran/Dev/react-slidy/package.json","includedInParent":true,"mtime":1521562679188},{"name":"/Users/miguelangel.duran/Dev/react-slidy/node_modules/lowlight/node_modules/highlight.js/package.json","includedInParent":true,"mtime":1520272392441}],"generated":{"js":"module.exports = function(hljs) {\n  var DETAILS = {\n    className: 'string',\n    begin: '\\\\[\\n(multipart)?', end: '\\\\]\\n'\n  };\n  var TIME = {\n    className: 'string',\n    begin: '\\\\d{4}-\\\\d{2}-\\\\d{2}(\\\\s+)\\\\d{2}:\\\\d{2}:\\\\d{2}\\.\\\\d+Z'\n  };\n  var PROGRESSVALUE = {\n    className: 'string',\n    begin: '(\\\\+|-)\\\\d+'\n  };\n  var KEYWORDS = {\n    className: 'keyword',\n    relevance: 10,\n    variants: [\n      { begin: '^(test|testing|success|successful|failure|error|skip|xfail|uxsuccess)(:?)\\\\s+(test)?' },\n      { begin: '^progress(:?)(\\\\s+)?(pop|push)?' },\n      { begin: '^tags:' },\n      { begin: '^time:' }\n    ],\n  };\n  return {\n    case_insensitive: true,\n    contains: [\n      DETAILS,\n      TIME,\n      PROGRESSVALUE,\n      KEYWORDS\n    ]\n  };\n};","map":{"mappings":[{"source":"../node_modules/lowlight/node_modules/highlight.js/lib/languages/subunit.js","original":{"line":1,"column":0},"generated":{"line":1,"column":0}},{"source":"../node_modules/lowlight/node_modules/highlight.js/lib/languages/subunit.js","original":{"line":2,"column":0},"generated":{"line":2,"column":0}},{"source":"../node_modules/lowlight/node_modules/highlight.js/lib/languages/subunit.js","original":{"line":3,"column":0},"generated":{"line":3,"column":0}},{"source":"../node_modules/lowlight/node_modules/highlight.js/lib/languages/subunit.js","original":{"line":4,"column":0},"generated":{"line":4,"column":0}},{"source":"../node_modules/lowlight/node_modules/highlight.js/lib/languages/subunit.js","original":{"line":5,"column":0},"generated":{"line":5,"column":0}},{"source":"../node_modules/lowlight/node_modules/highlight.js/lib/languages/subunit.js","original":{"line":6,"column":0},"generated":{"line":6,"column":0}},{"source":"../node_modules/lowlight/node_modules/highlight.js/lib/languages/subunit.js","original":{"line":7,"column":0},"generated":{"line":7,"column":0}},{"source":"../node_modules/lowlight/node_modules/highlight.js/lib/languages/subunit.js","original":{"line":8,"column":0},"generated":{"line":8,"column":0}},{"source":"../node_modules/lowlight/node_modules/highlight.js/lib/languages/subunit.js","original":{"line":9,"column":0},"generated":{"line":9,"column":0}},{"source":"../node_modules/lowlight/node_modules/highlight.js/lib/languages/subunit.js","original":{"line":10,"column":0},"generated":{"line":10,"column":0}},{"source":"../node_modules/lowlight/node_modules/highlight.js/lib/languages/subunit.js","original":{"line":11,"column":0},"generated":{"line":11,"column":0}},{"source":"../node_modules/lowlight/node_modules/highlight.js/lib/languages/subunit.js","original":{"line":12,"column":0},"generated":{"line":12,"column":0}},{"source":"../node_modules/lowlight/node_modules/highlight.js/lib/languages/subunit.js","original":{"line":13,"column":0},"generated":{"line":13,"column":0}},{"source":"../node_modules/lowlight/node_modules/highlight.js/lib/languages/subunit.js","original":{"line":14,"column":0},"generated":{"line":14,"column":0}},{"source":"../node_modules/lowlight/node_modules/highlight.js/lib/languages/subunit.js","original":{"line":15,"column":0},"generated":{"line":15,"column":0}},{"source":"../node_modules/lowlight/node_modules/highlight.js/lib/languages/subunit.js","original":{"line":16,"column":0},"generated":{"line":16,"column":0}},{"source":"../node_modules/lowlight/node_modules/highlight.js/lib/languages/subunit.js","original":{"line":17,"column":0},"generated":{"line":17,"column":0}},{"source":"../node_modules/lowlight/node_modules/highlight.js/lib/languages/subunit.js","original":{"line":18,"column":0},"generated":{"line":18,"column":0}},{"source":"../node_modules/lowlight/node_modules/highlight.js/lib/languages/subunit.js","original":{"line":19,"column":0},"generated":{"line":19,"column":0}},{"source":"../node_modules/lowlight/node_modules/highlight.js/lib/languages/subunit.js","original":{"line":20,"column":0},"generated":{"line":20,"column":0}},{"source":"../node_modules/lowlight/node_modules/highlight.js/lib/languages/subunit.js","original":{"line":21,"column":0},"generated":{"line":21,"column":0}},{"source":"../node_modules/lowlight/node_modules/highlight.js/lib/languages/subunit.js","original":{"line":22,"column":0},"generated":{"line":22,"column":0}},{"source":"../node_modules/lowlight/node_modules/highlight.js/lib/languages/subunit.js","original":{"line":23,"column":0},"generated":{"line":23,"column":0}},{"source":"../node_modules/lowlight/node_modules/highlight.js/lib/languages/subunit.js","original":{"line":24,"column":0},"generated":{"line":24,"column":0}},{"source":"../node_modules/lowlight/node_modules/highlight.js/lib/languages/subunit.js","original":{"line":25,"column":0},"generated":{"line":25,"column":0}},{"source":"../node_modules/lowlight/node_modules/highlight.js/lib/languages/subunit.js","original":{"line":26,"column":0},"generated":{"line":26,"column":0}},{"source":"../node_modules/lowlight/node_modules/highlight.js/lib/languages/subunit.js","original":{"line":27,"column":0},"generated":{"line":27,"column":0}},{"source":"../node_modules/lowlight/node_modules/highlight.js/lib/languages/subunit.js","original":{"line":28,"column":0},"generated":{"line":28,"column":0}},{"source":"../node_modules/lowlight/node_modules/highlight.js/lib/languages/subunit.js","original":{"line":29,"column":0},"generated":{"line":29,"column":0}},{"source":"../node_modules/lowlight/node_modules/highlight.js/lib/languages/subunit.js","original":{"line":30,"column":0},"generated":{"line":30,"column":0}},{"source":"../node_modules/lowlight/node_modules/highlight.js/lib/languages/subunit.js","original":{"line":31,"column":0},"generated":{"line":31,"column":0}},{"source":"../node_modules/lowlight/node_modules/highlight.js/lib/languages/subunit.js","original":{"line":32,"column":0},"generated":{"line":32,"column":0}},{"source":"../node_modules/lowlight/node_modules/highlight.js/lib/languages/subunit.js","original":{"line":33,"column":0},"generated":{"line":33,"column":0}}],"sources":{"../node_modules/lowlight/node_modules/highlight.js/lib/languages/subunit.js":"module.exports = function(hljs) {\n  var DETAILS = {\n    className: 'string',\n    begin: '\\\\[\\n(multipart)?', end: '\\\\]\\n'\n  };\n  var TIME = {\n    className: 'string',\n    begin: '\\\\d{4}-\\\\d{2}-\\\\d{2}(\\\\s+)\\\\d{2}:\\\\d{2}:\\\\d{2}\\.\\\\d+Z'\n  };\n  var PROGRESSVALUE = {\n    className: 'string',\n    begin: '(\\\\+|-)\\\\d+'\n  };\n  var KEYWORDS = {\n    className: 'keyword',\n    relevance: 10,\n    variants: [\n      { begin: '^(test|testing|success|successful|failure|error|skip|xfail|uxsuccess)(:?)\\\\s+(test)?' },\n      { begin: '^progress(:?)(\\\\s+)?(pop|push)?' },\n      { begin: '^tags:' },\n      { begin: '^time:' }\n    ],\n  };\n  return {\n    case_insensitive: true,\n    contains: [\n      DETAILS,\n      TIME,\n      PROGRESSVALUE,\n      KEYWORDS\n    ]\n  };\n};"},"lineCount":33}},"hash":"c7e6ab1f9bf8e3f89d030a3085c3dbd7","cacheData":{"env":{}}}